pillowmd/CustomMarkdownRenderer.py
pillowmd/CustomMarkdownRenderer.pyi
pillowmd/SampleStyles.py
pillowmd/Setting.py
pillowmd/__init__.py
pillowmd/data/fonts/STIXTwoMath-Regular.ttf
pillowmd/data/fonts/smSans.ttf
pillowmd/data/fonts/unifont.ttf
pillowmd/data/fonts/yahei.ttf
pillowmd/data/logo/sample.png
pillowmd/data/paint/sample.png
pillowmd/data/sample_styles/Sample1/cover.png
pillowmd/data/sample_styles/Sample1/elements.json
pillowmd/data/sample_styles/Sample1/setting.json
pillowmd/data/sample_styles/Sample1/imgs/1.2.200.png
pillowmd/data/sample_styles/Sample1/imgs/2.2.200.png
pillowmd/data/sample_styles/Sample1/imgs/2.3.200.png
pillowmd/data/sample_styles/Sample1/imgs/2.aa.png
pillowmd/data/sample_styles/Sample1/imgs/3.2.200.png
pillowmd/data/sample_styles/Sample1/imgs/4.2.200.png
pillowmd/data/sample_styles/Sample1/imgs/4.3.200.png
pillowmd/data/sample_styles/Sample1/imgs/5.2.200.png
pillowmd/data/sample_styles/Sample1/imgs/5.3.200.png
pillowmd/data/sample_styles/Sample1/imgs/6.2.200.png
pillowmd/data/sample_styles/Sample1/imgs/7.2.200.png
pillowmd/data/sample_styles/Sample1/imgs/7.3.200.png
pillowmd/data/sample_styles/Sample1/imgs/8.2.200.png
pillowmd/data/sample_styles/Sample1/imgs/9.2.200.png
pillowmd/data/sample_styles/Sample2/cover.png
pillowmd/data/sample_styles/Sample2/elements.json
pillowmd/data/sample_styles/Sample2/setting.json
pillowmd/data/sample_styles/Sample2/imgs/1_1.png
pillowmd/data/sample_styles/Sample2/imgs/1_10.png
pillowmd/data/sample_styles/Sample2/imgs/1_11.png
pillowmd/data/sample_styles/Sample2/imgs/1_12.png
pillowmd/data/sample_styles/Sample2/imgs/1_13.png
pillowmd/data/sample_styles/Sample2/imgs/1_2.png
pillowmd/data/sample_styles/Sample2/imgs/1_3.png
pillowmd/data/sample_styles/Sample2/imgs/1_4.png
pillowmd/data/sample_styles/Sample2/imgs/1_5.png
pillowmd/data/sample_styles/Sample2/imgs/1_6.png
pillowmd/data/sample_styles/Sample2/imgs/1_7.png
pillowmd/data/sample_styles/Sample2/imgs/1_8.png
pillowmd-0.7.3.dist-info/licenses/LICENSE
pillowmd-0.7.3.dist-info/METADATA
pillowmd-0.7.3.dist-info/WHEEL
pillowmd-0.7.3.dist-info/top_level.txt
pillowmd-0.7.3.dist-info/RECORD
