Metadata-Version: 2.4
Name: pillowmd
Version: 0.7.3
Summary: 基于 Pillow 的可自定义 Markdown 风格渲染器，渲染速度快且易于配置
Author-email: 迷梦龙 <614675349@qq.com>
License-Expression: MIT
Project-URL: homepage, https://github.com/Monody-S/CustomMarkdownImage
Keywords: markdown,pillow,image,rendering,custom
Classifier: Development Status :: 5 - Production/Stable
Classifier: Intended Audience :: Developers
Classifier: Natural Language :: Chinese (Simplified)
Classifier: Programming Language :: Python :: 3
Classifier: Programming Language :: Python :: 3.10
Classifier: Programming Language :: Python :: 3.11
Classifier: Programming Language :: Python :: 3.12
Classifier: Programming Language :: Python :: 3.13
Classifier: Operating System :: OS Independent
Classifier: Topic :: Software Development :: Libraries :: Python Modules
Requires-Python: <4.0,>=3.10
License-File: LICENSE
Requires-Dist: pillow
Requires-Dist: pyyaml
Requires-Dist: httpx
Requires-Dist: fonttools
Requires-Dist: pillowlatex>=0.1.4
Dynamic: license-file
